pymesh2-0.1.14.data/purelib/pymesh/Boundary.py
pymesh2-0.1.14.data/purelib/pymesh/CSGTree.py
pymesh2-0.1.14.data/purelib/pymesh/Mesh.py
pymesh2-0.1.14.data/purelib/pymesh/PyMeshSetting.py
pymesh2-0.1.14.data/purelib/pymesh/Solver.py
pymesh2-0.1.14.data/purelib/pymesh/TestCase.py
pymesh2-0.1.14.data/purelib/pymesh/VoxelGrid.py
pymesh2-0.1.14.data/purelib/pymesh/__init__.py
pymesh2-0.1.14.data/purelib/pymesh/aabb_tree.py
pymesh2-0.1.14.data/purelib/pymesh/boolean.py
pymesh2-0.1.14.data/purelib/pymesh/boolean_unsupported.py
pymesh2-0.1.14.data/purelib/pymesh/cell_partition.py
pymesh2-0.1.14.data/purelib/pymesh/material.py
pymesh2-0.1.14.data/purelib/pymesh/matrixio.py
pymesh2-0.1.14.data/purelib/pymesh/meshio.py
pymesh2-0.1.14.data/purelib/pymesh/minkowski_sum.py
pymesh2-0.1.14.data/purelib/pymesh/outerhull.py
pymesh2-0.1.14.data/purelib/pymesh/predicates.py
pymesh2-0.1.14.data/purelib/pymesh/selfintersection.py
pymesh2-0.1.14.data/purelib/pymesh/slice_mesh.py
pymesh2-0.1.14.data/purelib/pymesh/tetrahedralize.py
pymesh2-0.1.14.data/purelib/pymesh/timethis.py
pymesh2-0.1.14.data/purelib/pymesh/triangulate.py
pymesh2-0.1.14.data/purelib/pymesh/version.py
pymesh2-0.1.14.data/purelib/pymesh/winding_number.py
pymesh2-0.1.14.data/purelib/pymesh/lib/_PyAssembler.so
pymesh2-0.1.14.data/purelib/pymesh/lib/_PyBoolean.so
pymesh2-0.1.14.data/purelib/pymesh/lib/_PyCGAL.so
pymesh2-0.1.14.data/purelib/pymesh/lib/_PyConvexHull.so
pymesh2-0.1.14.data/purelib/pymesh/lib/_PyEigenUtils.so
pymesh2-0.1.14.data/purelib/pymesh/lib/_PyEnvelope.so
pymesh2-0.1.14.data/purelib/pymesh/lib/_PyIGL.so
pymesh2-0.1.14.data/purelib/pymesh/lib/_PyMesh.so
pymesh2-0.1.14.data/purelib/pymesh/lib/_PyMeshUtils.so
pymesh2-0.1.14.data/purelib/pymesh/lib/_PyOuterHull.so
pymesh2-0.1.14.data/purelib/pymesh/lib/_PyPredicates.so
pymesh2-0.1.14.data/purelib/pymesh/lib/_PySelfIntersection.so
pymesh2-0.1.14.data/purelib/pymesh/lib/_PySparseSolver.so
pymesh2-0.1.14.dist-info/DESCRIPTION.rst
pymesh2-0.1.14.dist-info/METADATA
pymesh2-0.1.14.dist-info/RECORD
pymesh2-0.1.14.dist-info/WHEEL
pymesh2-0.1.14.dist-info/metadata.json
pymesh2-0.1.14.dist-info/top_level.txt
