Metadata-Version: 2.0
Name: pymesh2
Version: 0.1.14
Summary: Mesh Processing for Python
Home-page: https://github.com/qnzhou/PyMesh
Author: Qingnan Zhou
Author-email: qnzhou@gmail.com
License: MPL
Download-URL: https://github.com/qnzhou/PyMesh/tarball/v0.1
Platform: UNKNOWN
